{
    "type": "MendProjector",
	"name": "自塑装甲",
	"description": "使用自塑合金制作的装甲，通电会自动修复",
	"health": 85000,
	"size": 2,
	"range": 1,
	"reload": 60,
	"healPercent": 0.1,
	"phaseBoost":10,
	"color": "00000000",
	"phaseRangeBoost":0,
	"canOverdrive": false,
	"absorbLasers":true,
	"insulated":false,
	"consumes":{
		"power": 10,
	},
	"requirements": [
	{ "item":"titanium","amount":1200},
	{ "item":"plastanium","amount":800},
	{ "item":"surge-alloy","amount":800},
	{ "item":"饱和火力-莱普合金","amount":800},
	{ "item":"自塑合金","amount":800},
	{ "item":"天临协议","amount":3}
	],
	"category": "defense",
	"research":"星际实验室"
}